Workbook

Sheet Dashboard
B2: EXAMPLE MULTI-ACADEMY TRUST — Management Accounts
B3: Period 9 · May 2026 · Academic year 2025/26 · Prepared in line with DfE Academy Trust Handbook & good practice guidance
B5: YTD INCOME | E5: YTD EXPENDITURE | H5: YTD SURPLUS / (DEFICIT) | K5: FY FORECAST SURPLUS
B6: ='Income & Expenditure'!C14 | E6: ='Income & Expenditure'!C25 | H6: ='Income & Expenditure'!C27 | K6: ='Income & Expenditure'!H27
B8: vs YTD budget — see I&E tab | E8: vs YTD budget — see I&E tab | H8: vs budget — favourable | K8: vs FY budget — favourable
B10: CASH IN BANK | E10: REVENUE RESERVES | H10: STAFF COSTS % INCOME | K10: PUPILS ON ROLL
B11: ='Balance Sheet'!C12 | E11: ='Balance Sheet'!C22+'Balance Sheet'!C24 | H11: 0.787 | K11: 1886
B13: ● 56 days cash — on target | E13: ● 12.3% of income — on target | H13: ● vs 80% ceiling — on target | K13: ● 94.3% of capacity — watch
B15: Income vs expenditure — monthly (£k) | H15: Cash balance — actual vs forecast (£k)
B33: Monthly surplus / (deficit) vs budget (£k) | H33: At a glance
H35: ● Finances on track: YTD surplus £52k ahead of budget; FY forecast surplus improved to £180k.
H38: ● Liquidity strong: 56 days cash, reserves 12.3% of income — inside the 5–15% policy range.
H41: ● Premises costs £45k adverse — estates survey commissioned (see Commentary).
H44: ● Pupil numbers 94.3% of capacity — October census key risk to 2026/27 GAG.
H47: ● Staff costs 78.7% of income — below the 80% sustainability ceiling.
B51: Contents: Income & Expenditure · Balance Sheet · Cash Flow · KPIs · Commentary · Monthly Data. Pack covers the items the Academy Trust Handbook requires boards to monitor (I&E, variance to budget, cash flow and balance sheet). All figures illustrative.

Sheet Monthly Data
B2: Monthly Data
B3: Working data that drives the Dashboard charts — enter monthly actuals here
B5: Month | C5: Income Actual £k | D5: Income Budget £k | E5: Expenditure Actual £k | F5: Expenditure Budget £k | G5: Cash Actual £k | H5: Cash Forecast £k | I5: Surplus Actual £k | J5: Surplus Budget £k
B6: Sep | C6: 1380 | D6: 1350 | E6: 1290 | F6: 1300 | G6: 2350 | H6: 2350 | I6: =IF(C6="","",C6-E6) | J6: =D6-F6
B7: Oct | C7: 1295 | D7: 1300 | E7: 1310 | F7: 1295 | G7: 2310 | H7: 2315 | I7: =IF(C7="","",C7-E7) | J7: =D7-F7
B8: Nov | C8: 1310 | D8: 1300 | E8: 1285 | F8: 1290 | G8: 2330 | H8: 2325 | I8: =IF(C8="","",C8-E8) | J8: =D8-F8
B9: Dec | C9: 1290 | D9: 1300 | E9: 1330 | F9: 1320 | G9: 2280 | H9: 2285 | I9: =IF(C9="","",C9-E9) | J9: =D9-F9
B10: Jan | C10: 1335 | D10: 1320 | E10: 1295 | F10: 1300 | G10: 2335 | H10: 2330 | I10: =IF(C10="","",C10-E10) | J10: =D10-F10
B11: Feb | C11: 1300 | D11: 1310 | E11: 1305 | F11: 1300 | G11: 2330 | H11: 2335 | I11: =IF(C11="","",C11-E11) | J11: =D11-F11
B12: Mar | C12: 1345 | D12: 1330 | E12: 1290 | F12: 1295 | G12: 2390 | H12: 2380 | I12: =IF(C12="","",C12-E12) | J12: =D12-F12
B13: Apr | C13: 1310 | D13: 1320 | E13: 1315 | F13: 1310 | G13: 2385 | H13: 2390 | I13: =IF(C13="","",C13-E13) | J13: =D13-F13
B14: May | C14: 1352 | D14: 1330 | E14: 1298 | F14: 1305 | G14: 2440 | H14: 2430 | I14: =IF(C14="","",C14-E14) | J14: =D14-F14
B15: Jun | D15: 1330 | F15: 1305 | H15: 2455 | I15: =IF(C15="","",C15-E15) | J15: =D15-F15
B16: Jul | D16: 1340 | F16: 1320 | H16: 2470 | I16: =IF(C16="","",C16-E16) | J16: =D16-F16
B17: Aug | D17: 1370 | F17: 1360 | H17: 2480 | I17: =IF(C17="","",C17-E17) | J17: =D17-F17

Sheet Income & Expenditure
B2: Income & Expenditure
B3: Year to date Period 9 (May 2026) and full-year forecast | Academic year 2025/26 | £
C5: YTD Actual | D5: YTD Budget | E5: YTD Variance | F5: Var % | G5: FY Budget | H5: FY Forecast | I5: FY Variance
B7: INCOME
B8: General Annual Grant (GAG) | C8: 10125000 | D8: 10050000 | E8: =C8-D8 | F8: =IF(D8=0,0,(C8-D8)/D8) | G8: 13400000 | H8: 13480000 | I8: =H8-G8
B9: Other DfE / ESFA grants | C9: 610000 | D9: 585000 | E9: =C9-D9 | F9: =IF(D9=0,0,(C9-D9)/D9) | G9: 780000 | H9: 805000 | I9: =H9-G9
B10: Pupil premium | C10: 565000 | D10: 560000 | E10: =C10-D10 | F10: =IF(D10=0,0,(C10-D10)/D10) | G10: 745000 | H10: 748000 | I10: =H10-G10
B11: Local authority grants (inc. SEN) | C11: 402000 | D11: 430000 | E11: =C11-D11 | F11: =IF(D11=0,0,(C11-D11)/D11) | G11: 573000 | H11: 545000 | I11: =H11-G11
B12: Catering & lettings income | C12: 158000 | D12: 170000 | E12: =C12-D12 | F12: =IF(D12=0,0,(C12-D12)/D12) | G12: 227000 | H12: 212000 | I12: =H12-G12
B13: Donations & fundraising | C13: 57000 | D13: 45000 | E13: =C13-D13 | F13: =IF(D13=0,0,(C13-D13)/D13) | G13: 60000 | H13: 71000 | I13: =H13-G13
B14: Total income | C14: =SUM(C8:C13) | D14: =SUM(D8:D13) | E14: =C14-D14 | F14: =IF(D14=0,0,(C14-D14)/D14) | G14: =SUM(G8:G13) | H14: =SUM(H8:H13) | I14: =H14-G14
B16: EXPENDITURE
B17: Teaching staff | C17: 5430000 | D17: 5380000 | E17: =C17-D17 | F17: =IF(D17=0,0,(C17-D17)/D17) | G17: 7173000 | H17: 7240000 | I17: =H17-G17
B18: Education support staff | C18: 1488000 | D18: 1520000 | E18: =C18-D18 | F18: =IF(D18=0,0,(C18-D18)/D18) | G18: 2027000 | H18: 1985000 | I18: =H18-G18
B19: Admin & leadership staff | C19: 1356000 | D19: 1340000 | E19: =C19-D19 | F19: =IF(D19=0,0,(C19-D19)/D19) | G19: 1787000 | H19: 1802000 | I19: =H19-G19
B20: Indirect staff costs (supply, dev.) | C20: 302000 | D20: 340000 | E20: =C20-D20 | F20: =IF(D20=0,0,(C20-D20)/D20) | G20: 453000 | H20: 420000 | I20: =H20-G20
B21: Premises & estates (inc. PFI/maint.) | C21: 985000 | D21: 940000 | E21: =C21-D21 | F21: =IF(D21=0,0,(C21-D21)/D21) | G21: 1253000 | H21: 1310000 | I21: =H21-G21
B22: Educational supplies & ICT | C22: 738000 | D22: 760000 | E22: =C22-D22 | F22: =IF(D22=0,0,(C22-D22)/D22) | G22: 1013000 | H22: 995000 | I22: =H22-G22
B23: Catering supplies | C23: 331000 | D23: 325000 | E23: =C23-D23 | F23: =IF(D23=0,0,(C23-D23)/D23) | G23: 433000 | H23: 441000 | I23: =H23-G23
B24: Other support costs & professional | C24: 788000 | D24: 810000 | E24: =C24-D24 | F24: =IF(D24=0,0,(C24-D24)/D24) | G24: 1080000 | H24: 1056000 | I24: =H24-G24
B25: Total expenditure | C25: =SUM(C17:C24) | D25: =SUM(D17:D24) | E25: =C25-D25 | F25: =IF(D25=0,0,(C25-D25)/D25) | G25: =SUM(G17:G24) | H25: =SUM(H17:H24) | I25: =H25-G25
B27: In-year surplus / (deficit) | C27: =C14-C25 | D27: =D14-D25 | E27: =C27-D27 | F27: =IF(D27=0,0,(C27-D27)/MAX(1,ABS(D27))) | G27: =G14-G25 | H27: =H14-H25 | I27: =H27-G27
B29: Variance basis: income — favourable = actual above budget; expenditure — favourable = actual below budget. Variances over ±5% or ±£50k should be explained in the Commentary tab (DfE good practice).

Sheet Balance Sheet
B2: Balance Sheet
B3: As at 31 May 2026 (Period 9) with prior year-end comparative | £
C5: 31 May 2026 | D5: 31 Aug 2025 | E5: Movement
B6: FIXED ASSETS
B7: Tangible fixed assets (land & buildings) | C7: 28450000 | D7: 28930000 | E7: =C7-D7
B8: Other tangible fixed assets (FF&E, ICT) | C8: 842000 | D8: 760000 | E8: =C8-D8
B9: Total fixed assets | C9: =SUM(C7:C8) | D9: =SUM(D7:D8) | E9: =C9-D9
B10: CURRENT ASSETS
B11: Debtors & prepayments | C11: 412000 | D11: 385000 | E11: =C11-D11
B12: Cash at bank and in hand | C12: 2440000 | D12: 2350000 | E12: =C12-D12
B13: Total current assets | C13: =SUM(C11:C12) | D13: =SUM(D11:D12) | E13: =C13-D13
B14: LIABILITIES
B15: Creditors: amounts due within one year | C15: -618000 | D15: -572000 | E15: =C15-D15
B16: Creditors: amounts due after one year | C16: -95000 | D16: -120000 | E16: =C16-D16
B17: Pension scheme liability (LGPS) | C17: -3120000 | D17: -3450000 | E17: =C17-D17
B18: Total liabilities | C18: =SUM(C15:C17) | D18: =SUM(D15:D17) | E18: =C18-D18
B19: NET ASSETS | C19: =C9+C13+C18 | D19: =D9+D13+D18 | E19: =C19-D19
B20: FUNDS / RESERVES
B21: Restricted fixed asset fund | C21: 29292000 | D21: 29690000 | E21: =C21-D21
B22: Restricted general fund (GAG) | C22: 738000 | D22: 540000 | E22: =C22-D22
B23: Restricted pension reserve | C23: 3120000 | D23: 3450000 | E23: =C23-D23
B24: Unrestricted general fund | C24: 1401000 | D24: 1503000 | E24: =C24-D24
B25: TOTAL FUNDS | C25: =SUM(C21:C24) | D25: =SUM(D21:D24) | E25: =C25-D25

Sheet Cash Flow
B2: Cash Flow Forecast
B3: 12-month profile, academic year 2025/26 — actuals to Period 9, forecast thereafter | £k
C5: Sep | D5: Oct | E5: Nov | F5: Dec | G5: Jan | H5: Feb | I5: Mar | J5: Apr | K5: May | L5: Jun * | M5: Jul * | N5: Aug * | O5: Total
B6: Receipts
B7: GAG & ESFA grant receipts | C7: 1180 | D7: 1125 | E7: 1125 | F7: 1125 | G7: 1160 | H7: 1130 | I7: 1165 | J7: 1140 | K7: 1170 | L7: 1155 | M7: 1165 | N7: 1190 | O7: =SUM(C7:N7)
B8: Other grants & LA income | C8: 115 | D8: 98 | E8: 102 | F8: 95 | G8: 104 | H8: 99 | I8: 106 | J8: 100 | K8: 108 | L8: 102 | M8: 101 | N8: 105 | O8: =SUM(C8:N8)
B9: Other income (catering etc.) | C9: 85 | D9: 72 | E9: 83 | F9: 70 | G9: 71 | H9: 71 | I9: 74 | J9: 70 | K9: 74 | L9: 73 | M9: 74 | N9: 75 | O9: =SUM(C9:N9)
B10: Total receipts | C10: =SUM(C7:C9) | D10: =SUM(D7:D9) | E10: =SUM(E7:E9) | F10: =SUM(F7:F9) | G10: =SUM(G7:G9) | H10: =SUM(H7:H9) | I10: =SUM(I7:I9) | J10: =SUM(J7:J9) | ... O10: =SUM(O7:O9)
B11: Payments
B12: Staff costs (net pay, tax, pensions) | C12: 955 | D12: 962 | E12: 958 | F12: 975 | G12: 960 | H12: 964 | I12: 956 | J12: 968 | K12: 961 | L12: 962 | M12: 975 | N12: 1005 | O12: =SUM(C12:N12)
B13: Premises & estates | C13: 110 | D13: 118 | E13: 105 | F13: 128 | G13: 112 | H13: 109 | I13: 104 | J13: 115 | K13: 103 | L13: 108 | M13: 112 | N13: 118 | O13: =SUM(C13:N13)
B14: Supplies, ICT & catering | C14: 148 | D14: 152 | E14: 145 | F14: 150 | G14: 146 | H14: 150 | I14: 148 | J14: 152 | K14: 147 | L14: 148 | M14: 152 | N14: 158 | O14: =SUM(C14:N14)
B15: Capital expenditure | C15: 77 | D15: 78 | E15: 77 | F15: 77 | G15: 77 | H15: 82 | I15: 82 | J15: 80 | K15: 87 | L15: 87 | M15: 81 | N15: 79 | O15: =SUM(C15:N15)
B16: Total payments | C16: =SUM(C12:C15) | D16: =SUM(D12:D15) | E16: =SUM(E12:E15) | F16: =SUM(F12:F15) | G16: =SUM(G12:G15) | H16: =SUM(H12:H15) | I16: =SUM(I12:I15) | J16: =SUM(J12:J15) | ... O16: =SUM(O12:O15)
B17: Net cash inflow / (outflow) | C17: =C10-C16 | D17: =D10-D16 | E17: =E10-E16 | F17: =F10-F16 | G17: =G10-G16 | H17: =H10-H16 | I17: =I10-I16 | J17: =J10-J16 | ... O17: =O10-O16
B18: Opening balance | C18: 2255 | D18: =C19 | E18: =D19 | F18: =E19 | G18: =F19 | H18: =G19 | I18: =H19 | J18: =I19 | K18: =J19 | ... N18: =M19
B19: Closing balance | C19: =C18+C17 | D19: =D18+D17 | E19: =E18+E17 | F19: =F18+F17 | G19: =G18+G17 | H19: =H18+H17 | I19: =I18+I17 | J19: =J18+J17 | ... N19: =N18+N17
B21: * Months marked with an asterisk are forecast. All figures £k. Closing balance highlights red if it falls below the trust's minimum cash policy (illustrative £1,300k ≈ 30 days of expenditure).

Sheet KPIs
B2: Key Performance Indicators
B3: DfE benchmark metrics — RAG rated against trust targets
B5: Indicator | C5: Actual | D5: Target / Benchmark | E5: RAG | F5: Direction | G5: Notes
B6: Staff costs as % of total income | C6: 0.787 | D6: < 80% | E6: ● On target | F6: ▼ improving | G6: DfE benchmark: most trusts 70–80%. Includes all staff cost lines.
B7: Revenue reserves as % of income | C7: 0.123 | D7: 5% – 15% | E7: ● On target | F7: ▲ rising | G7: Restricted general + unrestricted funds vs annualised income.
B8: Days cash in hand | C8: 56 | D8: > 30 days | E8: ● On target | F8: ▲ rising | G8: Cash balance ÷ average daily expenditure.
B9: YTD I&E variance to budget | C9: 0.012 | D9: ± 2% | E9: ● On target | F9: — stable | G9: Net surplus variance as % of budgeted income.
B10: Pupil numbers vs capacity | C10: 0.943 | D10: > 95% | E10: ● Watch | F10: ▼ falling | G10: 1,886 on roll vs 2,000 capacity. October census drives GAG lag.
B11: Income per pupil | C11: 6290 | D11: Benchmark £6,150 | E11: ● On target | F11: ▲ rising | G11: Compare via DfE Schools Financial Benchmarking service.
B12: Average teacher cost | C12: 58400 | D12: Benchmark £57,200 | E12: ● Watch | F12: ▲ rising | G12: Monitor pay award and pension employer contribution impact.
B13: Energy & estates cost per m² | C13: 31.2 | D13: Benchmark £29.50 | E13: ● Watch | F13: ▲ rising | G13: Above benchmark — estates review under way (see Commentary).

Sheet Commentary
B2: Variance Commentary & Actions
B3: Explain variances > ±5% or ±£50k, risks, and mitigating actions
B5: Area | C5: Variance | D5: Explanation | E5: Action / Owner | F5: Status
B6: GAG income | C6: +£75k YTD | D6: In-year growth funding confirmed for September bulge class. | E6: Reflect in FY forecast — done. CFO | F6: Closed
B7: Premises & estates | C7: −£45k YTD (adverse) | D7: Reactive maintenance at two sites plus winter energy usage above plan. | E7: Estates condition survey commissioned; quotes for boiler replacement. Estates Manager | F7: Open
B8: LA / SEN income | C8: −£28k YTD (adverse) | D8: EHCP top-up payments from LA running behind invoicing. | E8: Escalated with LA; aged debt review monthly. Finance Officer | F8: Open
B9: Supply & cover costs | C9: +£38k YTD (favourable) | D9: Lower sickness absence than budget assumption. | E9: Hold favourable variance; do not release until P11. CFO | F9: Monitor
